renew/__init__.py
renew/_inspection.py
renew/_mold.py
renew/_py_lang.py
renew/_serializer.py
renew-0.5.4.dist-info/LICENSE
renew-0.5.4.dist-info/METADATA
renew-0.5.4.dist-info/WHEEL
renew-0.5.4.dist-info/top_level.txt
renew-0.5.4.dist-info/RECORD
