Metadata-Version: 2.1
Name: renew
Version: 0.5.4
Summary: Gives a reproducible manner to your objects and can serialize them in 100% pythonic format.
Home-page: https://gitlab.com/kamichal/renew
Author: Michał Kaczmarczyk
Author-email: michal.s.kaczmarczyk@gmail.com
Maintainer: Michał Kaczmarczyk
Maintainer-email: michal.s.kaczmarczyk@gmail.com
License: MIT license
Platform: UNKNOWN
Classifier: Development Status :: 4 - Beta
Classifier: Intended Audience :: Developers
Classifier: Topic :: Software Development
Classifier: Topic :: Software Development :: Code Generators
Classifier: Programming Language :: Python
Classifier: Programming Language :: Python :: 2
Classifier: Programming Language :: Python :: 2.7
Classifier: Programming Language :: Python :: 3
Classifier: Programming Language :: Python :: 3.4
Classifier: Programming Language :: Python :: 3.5
Classifier: Programming Language :: Python :: 3.6
Classifier: Programming Language :: Python :: 3.7
Classifier: Programming Language :: Python :: Implementation :: PyPy
Classifier: Operating System :: OS Independent
Classifier: License :: OSI Approved :: MIT License
Requires: six
Requires-Dist: six
